<annotation>
	<folder>Images</folder>
	<filename>48867.jpg</filename>
	<path>C:\Users\darak\OneDrive\Desktop\2023_하계방학_스터디\라벨링\labelling-2차\Images\48867.jpg</path>
	<source>
		<database>Unknown</database>
	</source>
	<size>
		<width>648</width>
		<height>1152</height>
		<depth>3</depth>
	</size>
	<segmented>0</segmented>
	<object>
		<name>0</name>
		<pose>Unspecified</pose>
		<truncated>1</truncated>
		<difficult>0</difficult>
		<bndbox>
			<xmin>1</xmin>
			<ymin>46</ymin>
			<xmax>648</xmax>
			<ymax>951</ymax>
		</bndbox>
	</object>
</annotation>
