<annotation>
	<folder>selected</folder>
	<filename>9535.jpg</filename>
	<path>C:\Users\hephe\Desktop\train\selected\9535.jpg</path>
	<source>
		<database>Unknown</database>
	</source>
	<size>
		<width>478</width>
		<height>850</height>
		<depth>3</depth>
	</size>
	<segmented>0</segmented>
	<object>
		<name>0</name>
		<pose>Unspecified</pose>
		<truncated>1</truncated>
		<difficult>0</difficult>
		<bndbox>
			<xmin>1</xmin>
			<ymin>43</ymin>
			<xmax>478</xmax>
			<ymax>831</ymax>
		</bndbox>
	</object>
</annotation>
