<annotation>
	<folder>Product10K-bounding-box-labeling</folder>
	<filename>73785.jpg</filename>
	<path>C:\Users\JEON KYONG MIN\Desktop\Product10K-bounding-box-labeling\73785.jpg</path>
	<source>
		<database>Unknown</database>
	</source>
	<size>
		<width>297</width>
		<height>400</height>
		<depth>3</depth>
	</size>
	<segmented>0</segmented>
	<object>
		<name>0</name>
		<pose>Unspecified</pose>
		<truncated>0</truncated>
		<difficult>0</difficult>
		<bndbox>
			<xmin>157</xmin>
			<ymin>194</ymin>
			<xmax>245</xmax>
			<ymax>298</ymax>
		</bndbox>
	</object>
</annotation>
